Bottlechest-0.7.1.dist-info/DESCRIPTION.rst
Bottlechest-0.7.1.dist-info/METADATA
Bottlechest-0.7.1.dist-info/RECORD
Bottlechest-0.7.1.dist-info/WHEEL
Bottlechest-0.7.1.dist-info/metadata.json
Bottlechest-0.7.1.dist-info/top_level.txt
bottlechest/LICENSE
bottlechest/__init__.py
bottlechest/allnan.pyd
bottlechest/anynan.pyd
bottlechest/argpartsort.pyd
bottlechest/bincount.pyd
bottlechest/contingency.pyd
bottlechest/countnans.pyd
bottlechest/func.py
bottlechest/median.pyd
bottlechest/nanargmax.pyd
bottlechest/nanargmin.pyd
bottlechest/nanequal.pyd
bottlechest/nanmax.pyd
bottlechest/nanmean.pyd
bottlechest/nanmin.pyd
bottlechest/nanstd.pyd
bottlechest/nansum.pyd
bottlechest/nanvar.pyd
bottlechest/nn.pyd
bottlechest/partsort.pyd
bottlechest/rankdata.pyd
bottlechest/replace.pyd
bottlechest/ss.pyd
bottlechest/stats.pyd
bottlechest/valuecount.pyd
bottlechest/version.py
bottlechest/benchmark/__init__.py
bottlechest/benchmark/autotimeit.py
bottlechest/benchmark/bench.py
bottlechest/slow/__init__.py
bottlechest/slow/func.py
bottlechest/slow/move.py
bottlechest/src/__init__.py
bottlechest/src/makepyx.py
bottlechest/src/func/setup.py
bottlechest/src/template/__init__.py
bottlechest/src/template/package.py
bottlechest/src/template/template.py
bottlechest/src/template/func/__init__.py
bottlechest/src/template/func/allnan.py
bottlechest/src/template/func/anynan.py
bottlechest/src/template/func/argpartsort.py
bottlechest/src/template/func/bincount.py
bottlechest/src/template/func/contingency.py
bottlechest/src/template/func/countnans.py
bottlechest/src/template/func/median.py
bottlechest/src/template/func/nanargmax.py
bottlechest/src/template/func/nanargmin.py
bottlechest/src/template/func/nanequal.py
bottlechest/src/template/func/nanequal.w3d.py
bottlechest/src/template/func/nanmax.py
bottlechest/src/template/func/nanmean.py
bottlechest/src/template/func/nanmin.py
bottlechest/src/template/func/nanstd.py
bottlechest/src/template/func/nansum.py
bottlechest/src/template/func/nanvar.py
bottlechest/src/template/func/nn.py
bottlechest/src/template/func/partsort.py
bottlechest/src/template/func/rankdata.py
bottlechest/src/template/func/replace.py
