Metadata-Version: 2.0
Name: Bottlechest
Version: 0.7.1
Summary: Fast NumPy array functions written in Cython
Home-page: https://github.com/biolab/bottlechest
Author: Bioinformatics Laboratory, FRI UL
Author-email: contact@orange.biolab.si
License: Simplified BSD
Download-URL: https://github.com/biolab/bottlechest
Platform: OS Independent
Classifier: Development Status :: 4 - Beta
Classifier: Environment :: Console
Classifier: Intended Audience :: Science/Research
Classifier: License :: OSI Approved :: BSD License
Classifier: Operating System :: OS Independent
Classifier: Programming Language :: Cython
Classifier: Programming Language :: Python
Classifier: Programming Language :: Python :: 3
Classifier: Topic :: Scientific/Engineering
Requires: numpy
